MANIFEST.in
README.rst
VERSION.txt
pyproject.toml
setup.cfg
setup.py
sage/all__sagemath_meataxe.py
sage/libs/all__sagemath_meataxe.py
sage/libs/meataxe.pxd
sage/libs/meataxe.pyx
sage/matrix/all__sagemath_meataxe.py
sage/matrix/matrix_gfpn_dense.pxd
sage/matrix/matrix_gfpn_dense.pyx
sagemath_meataxe.egg-info/PKG-INFO
sagemath_meataxe.egg-info/SOURCES.txt
sagemath_meataxe.egg-info/dependency_links.txt
sagemath_meataxe.egg-info/requires.txt
sagemath_meataxe.egg-info/top_level.txt